README.txt
setup.py
NoseGrowl.egg-info/PKG-INFO
NoseGrowl.egg-info/SOURCES.txt
NoseGrowl.egg-info/dependency_links.txt
NoseGrowl.egg-info/entry_points.txt
NoseGrowl.egg-info/not-zip-safe
NoseGrowl.egg-info/requires.txt
NoseGrowl.egg-info/top_level.txt
nosegrowl/__init__.py
nosegrowl/growler.py