Metadata-Version: 1.0
Name: NoseGrowl
Version: 0.4
Summary: nose plugin for Growl notifications
Home-page: http://bitbucket.org/crankycoder/nosegrowl
Author: Victor Ng
Author-email: crankycoder@gmail.com
License: GNU LGPL
Platform: UNKNOWN
